nrp_cmd/__init__.py
nrp_cmd/converter.py
nrp_cmd/errors.py
nrp_cmd/progress.py
nrp_cmd/py.typed
nrp_cmd/rdm_compat.py
nrp_cmd/async_client/__init__.py
nrp_cmd/async_client/base_client.py
nrp_cmd/async_client/doi.py
nrp_cmd/async_client/connection/__init__.py
nrp_cmd/async_client/connection/auth.py
nrp_cmd/async_client/connection/aws_limits.py
nrp_cmd/async_client/connection/connection.py
nrp_cmd/async_client/connection/limiter.py
nrp_cmd/async_client/connection/response.py
nrp_cmd/async_client/connection/task_group.py
nrp_cmd/async_client/invenio/__init__.py
nrp_cmd/async_client/invenio/client.py
nrp_cmd/async_client/invenio/files.py
nrp_cmd/async_client/invenio/records.py
nrp_cmd/async_client/invenio/requests.py
nrp_cmd/async_client/invenio/transfer/__init__.py
nrp_cmd/async_client/invenio/transfer/base.py
nrp_cmd/async_client/invenio/transfer/local.py
nrp_cmd/async_client/invenio/transfer/multipart.py
nrp_cmd/async_client/invenio/transfer/registry.py
nrp_cmd/async_client/streams/__init__.py
nrp_cmd/async_client/streams/base.py
nrp_cmd/async_client/streams/bounded_stream.py
nrp_cmd/async_client/streams/file.py
nrp_cmd/async_client/streams/memory.py
nrp_cmd/async_client/streams/os.py
nrp_cmd/async_client/streams/progress.py
nrp_cmd/async_client/streams/stdin.py
nrp_cmd/cli/__init__.py
nrp_cmd/cli/arguments.py
nrp_cmd/cli/base.py
nrp_cmd/cli/cli.py
nrp_cmd/cli/repositories.py
nrp_cmd/cli/variables.py
nrp_cmd/cli/files/__init__.py
nrp_cmd/cli/files/delete.py
nrp_cmd/cli/files/download.py
nrp_cmd/cli/files/list.py
nrp_cmd/cli/files/table_formatters.py
nrp_cmd/cli/files/update.py
nrp_cmd/cli/files/upload.py
nrp_cmd/cli/records/__init__.py
nrp_cmd/cli/records/create.py
nrp_cmd/cli/records/delete.py
nrp_cmd/cli/records/download.py
nrp_cmd/cli/records/edit_record.py
nrp_cmd/cli/records/get.py
nrp_cmd/cli/records/metadata.py
nrp_cmd/cli/records/publish.py
nrp_cmd/cli/records/record_file_name.py
nrp_cmd/cli/records/retract.py
nrp_cmd/cli/records/scan.py
nrp_cmd-0.9.0.dist-info/METADATA
nrp_cmd-0.9.0.dist-info/WHEEL
nrp_cmd-0.9.0.dist-info/entry_points.txt
nrp_cmd-0.9.0.dist-info/RECORD
