Metadata-Version: 2.4
Name: nrp-cmd
Version: 0.9.0
Summary: Python and commandline client for NRP repositories
Requires-Python: <3.15,>=3.12
Requires-Dist: aiofile~=3.9.0
Requires-Dist: aiohttp[speedups]~=3.10.3
Requires-Dist: attrs
Requires-Dist: cattrs
Requires-Dist: click
Requires-Dist: deepmerge
Requires-Dist: humanize
Requires-Dist: merge-args
Requires-Dist: progressbar2
Requires-Dist: python-magic~=0.4.27
Requires-Dist: pyyaml~=6.0.2
Requires-Dist: requests
Requires-Dist: rich-click
Requires-Dist: stuf
Requires-Dist: tqdm
Requires-Dist: uvloop
Provides-Extra: pandas
Requires-Dist: pandas>=2.1.0; extra == 'pandas'
Provides-Extra: tests
Requires-Dist: mypy; extra == 'tests'
Requires-Dist: pytest-asyncio>=0.23; extra == 'tests'
Requires-Dist: pytest>=8.0.0; extra == 'tests'
Requires-Dist: ruff; extra == 'tests'
